BetterMD/__init__.py
BetterMD/__main__.py
BetterMD/typing.py
BetterMD/utils.py
BetterMD/elements/__init__.py
BetterMD/elements/a.py
BetterMD/elements/abbr.py
BetterMD/elements/acronym.py
BetterMD/elements/address.py
BetterMD/elements/area.py
BetterMD/elements/article.py
BetterMD/elements/aside.py
BetterMD/elements/audio.py
BetterMD/elements/base.py
BetterMD/elements/bd.py
BetterMD/elements/big.py
BetterMD/elements/blockquote.py
BetterMD/elements/body.py
BetterMD/elements/br.py
BetterMD/elements/button.py
BetterMD/elements/canvas.py
BetterMD/elements/caption.py
BetterMD/elements/center.py
BetterMD/elements/cite.py
BetterMD/elements/code.py
BetterMD/elements/col.py
BetterMD/elements/comment.py
BetterMD/elements/d.py
BetterMD/elements/data.py
BetterMD/elements/datalist.py
BetterMD/elements/del_.py
BetterMD/elements/details.py
BetterMD/elements/dialog.py
BetterMD/elements/dir.py
BetterMD/elements/div.py
BetterMD/elements/document.py
BetterMD/elements/embed.py
BetterMD/elements/fencedframe.py
BetterMD/elements/fieldset.py
BetterMD/elements/figure.py
BetterMD/elements/font.py
BetterMD/elements/footer.py
BetterMD/elements/form.py
BetterMD/elements/frame.py
BetterMD/elements/frameset.py
BetterMD/elements/h.py
BetterMD/elements/head.py
BetterMD/elements/header.py
BetterMD/elements/hgroup.py
BetterMD/elements/hr.py
BetterMD/elements/html.py
BetterMD/elements/i.py
BetterMD/elements/iframe.py
BetterMD/elements/img.py
BetterMD/elements/input.py
BetterMD/elements/ins.py
BetterMD/elements/kbd.py
BetterMD/elements/label.py
BetterMD/elements/legend.py
BetterMD/elements/li.py
BetterMD/elements/link.py
BetterMD/elements/main.py
BetterMD/elements/map.py
BetterMD/elements/mark.py
BetterMD/elements/marquee.py
BetterMD/elements/menu.py
BetterMD/elements/meta.py
BetterMD/elements/meter.py
BetterMD/elements/nav.py
BetterMD/elements/no.py
BetterMD/elements/object.py
BetterMD/elements/output.py
BetterMD/elements/p.py
BetterMD/elements/param.py
BetterMD/elements/picture.py
better_md-0.3.4.dist-info/licenses/LICENSE
better_md-0.3.4.dist-info/METADATA
better_md-0.3.4.dist-info/WHEEL
better_md-0.3.4.dist-info/top_level.txt
better_md-0.3.4.dist-info/RECORD
