Metadata-Version: 2.4
Name: Better-MD
Version: 0.3.4
Summary: A better markdown library
Home-page: https://github.com/Better-MD/better-md
Author: R5dan
Keywords: python,better markdown,markdown
Classifier: Development Status :: 3 - Alpha
Classifier: Intended Audience :: Developers
Classifier: Programming Language :: Python :: 3
Classifier: Operating System :: MacOS :: MacOS X
Classifier: Operating System :: Microsoft :: Windows
Classifier: Operating System :: POSIX :: Linux
License-File: LICENSE
Provides-Extra: tables
Requires-Dist: pandas==2.2.3; extra == "tables"
Dynamic: author
Dynamic: classifier
Dynamic: description
Dynamic: description-content-type
Dynamic: home-page
Dynamic: keywords
Dynamic: license-file
Dynamic: provides-extra
Dynamic: summary
